LICENSE
MANIFEST.in
README.md
pyproject.toml
requirements.txt
setup.cfg
setup.py
versioneer.py
elements_custom_fsspec.egg-info/PKG-INFO
elements_custom_fsspec.egg-info/SOURCES.txt
elements_custom_fsspec.egg-info/dependency_links.txt
elements_custom_fsspec.egg-info/not-zip-safe
elements_custom_fsspec.egg-info/requires.txt
elements_custom_fsspec.egg-info/top_level.txt
fsspec/__init__.py
fsspec/_version.py
fsspec/archive.py
fsspec/asyn.py
fsspec/caching.py
fsspec/callbacks.py
fsspec/compression.py
fsspec/config.py
fsspec/conftest.py
fsspec/core.py
fsspec/dircache.py
fsspec/exceptions.py
fsspec/fuse.py
fsspec/generic.py
fsspec/gui.py
fsspec/mapping.py
fsspec/parquet.py
fsspec/registry.py
fsspec/spec.py
fsspec/transaction.py
fsspec/utils.py
fsspec/implementations/__init__.py
fsspec/implementations/arrow.py
fsspec/implementations/cached.py
fsspec/implementations/dask.py
fsspec/implementations/dbfs.py
fsspec/implementations/dirfs.py
fsspec/implementations/dvc.py
fsspec/implementations/ftp.py
fsspec/implementations/git.py
fsspec/implementations/github.py
fsspec/implementations/hdfs.py
fsspec/implementations/http.py
fsspec/implementations/jupyter.py
fsspec/implementations/libarchive.py
fsspec/implementations/local.py
fsspec/implementations/memory.py
fsspec/implementations/reference.py
fsspec/implementations/sftp.py
fsspec/implementations/smb.py
fsspec/implementations/tar.py
fsspec/implementations/webhdfs.py
fsspec/implementations/zip.py