Metadata-Version: 2.1
Name: elements-custom-fsspec
Version: 2022.7.1.1
Summary: File-system specification
Home-page: http://github.com/fsspec/filesystem_spec
Maintainer: Martin Durant
Maintainer-email: mdurant@anaconda.com
License: BSD
Project-URL: Changelog, https://filesystem-spec.readthedocs.io/en/latest/changelog.html
Project-URL: Documentation, https://filesystem-spec.readthedocs.io/en/latest/
Keywords: file
Classifier: Development Status :: 4 - Beta
Classifier: Intended Audience :: Developers
Classifier: License :: OSI Approved :: BSD License
Classifier: Operating System :: OS Independent
Classifier: Programming Language :: Python :: 3.7
Classifier: Programming Language :: Python :: 3.8
Classifier: Programming Language :: Python :: 3.9
Classifier: Programming Language :: Python :: 3.10
Requires-Python: >=3.7
Provides-Extra: entrypoints
Provides-Extra: abfs
Provides-Extra: adl
Provides-Extra: dask
Provides-Extra: dropbox
Provides-Extra: gcs
Provides-Extra: git
Provides-Extra: github
Provides-Extra: gs
Provides-Extra: hdfs
Provides-Extra: arrow
Provides-Extra: http
Provides-Extra: sftp
Provides-Extra: s3
Provides-Extra: oci
Provides-Extra: smb
Provides-Extra: ssh
Provides-Extra: fuse
Provides-Extra: libarchive
Provides-Extra: gui
Provides-Extra: tqdm
License-File: LICENSE
